companies_house_codegen/__init__.py
companies_house_codegen/__main__.py
companies_house_codegen/argument.py
companies_house_codegen/codegen.py
companies_house_codegen/constants.py
companies_house_codegen/py.typed
companies_house_codegen/types.py
companies_house_codegen/utils.py
companies_house_codegen-0.2.1.dist-info/METADATA
companies_house_codegen-0.2.1.dist-info/WHEEL
companies_house_codegen-0.2.1.dist-info/entry_points.txt
companies_house_codegen-0.2.1.dist-info/licenses/LICENSE
companies_house_codegen-0.2.1.dist-info/RECORD
