Metadata-Version: 2.4
Name: companies-house-codegen
Version: 0.2.1
Summary: A simple but powerful toolkit for Companies House OpenAPI (Swagger 2.0) specifications.
Project-URL: Homepage, https://github.com/MMurape/companies-house-codegen
Project-URL: Repository, https://github.com/MMurape/companies-house-codegen
Project-URL: Issues, https://github.com/MMurape/companies-house-codegen/issues
Project-URL: Documentation, https://mmurape.github.io/companies-house-codegen
Author: Munyaradzi Murape
License: file = LICENSE
License-File: LICENSE
Keywords: API,Companies House,automation
Classifier: Development Status :: 3 - Alpha
Classifier: Environment :: Console
Classifier: Intended Audience :: Developers
Classifier: License :: OSI Approved :: MIT License
Classifier: Operating System :: OS Independent
Classifier: Programming Language :: Python
Classifier: Programming Language :: Python :: 3 :: Only
Classifier: Programming Language :: Python :: 3.8
Classifier: Programming Language :: Python :: 3.9
Classifier: Programming Language :: Python :: 3.10
Classifier: Programming Language :: Python :: 3.11
Classifier: Programming Language :: Python :: 3.12
Classifier: Programming Language :: Python :: 3.13
Classifier: Topic :: File Formats :: JSON :: JSON Schema
Classifier: Topic :: Software Development :: Libraries :: Python Modules
Classifier: Topic :: Software Development :: Quality Assurance
Requires-Python: >=3.8
Requires-Dist: pyyaml
Requires-Dist: typing-extensions
Provides-Extra: dev
Requires-Dist: mkdocs; extra == 'dev'
Requires-Dist: mkdocs-github-admonitions-plugin; extra == 'dev'
Requires-Dist: mkdocs-material>=8.0.0; extra == 'dev'
Requires-Dist: mkdocstrings[python]; extra == 'dev'
Requires-Dist: mypy; extra == 'dev'
Requires-Dist: pydantic>=2.0.0; extra == 'dev'
Requires-Dist: pymdown-extensions; extra == 'dev'
Requires-Dist: ruff; extra == 'dev'
Provides-Extra: docs
Requires-Dist: mkdocs; extra == 'docs'
Requires-Dist: mkdocs-github-admonitions-plugin; extra == 'docs'
Requires-Dist: mkdocs-material>=8.0.0; extra == 'docs'
Requires-Dist: mkdocstrings[python]; extra == 'docs'
Requires-Dist: pymdown-extensions; extra == 'docs'
Provides-Extra: pydantic
Requires-Dist: pydantic>=2.0.0; extra == 'pydantic'
